Metadata-Version: 2.1
Name: dependency-track-ng
Version: 0.0.6
Summary: A simple wrapper for the Dependency Track REST API. This is fork based on original work of Alvin Chen and his dependency-track library.
Home-page: https://github.com/jas02/dependency-track-python
Author: Alvin Chen, Lumir Jasiok
Author-email: sonoma001@gmail.com, lumir.jasiok@alfawolf.eu
Classifier: Programming Language :: Python :: 3
Classifier: License :: OSI Approved :: GNU General Public License v2 (GPLv2)
Classifier: Operating System :: OS Independent
Requires-Python: >=3.6
License-File: LICENSE.md
Requires-Dist: requests>=2.31.0
